{
  "name": "nebulum-mars-rovers",
  "origin": "voxgig-sdk",
  "def": "nebulum-mars-rovers_0.1.0.json",
  "main": {
    "kit": {
      "info": {
        "contact": {
          "name": "Nebulum",
          "url": "https://rovers.nebulum.one/"
        },
        "description": "Access real-time photos taken by Mars rovers Perseverance and Curiosity through NASA missions. Developers can retrieve images based on unique photo IDs, Earth dates, or Martian sols. This API offers efficient access to fascinating Mars exploration data for enthusiasts and researchers.",
        "servers": [
          {
            "description": "Production server",
            "url": "https://rovers.nebulum.one/api/v1"
          }
        ],
        "title": "Nebulum Mars Rovers API",
        "version": "1.0.0",
        "tagline": "Fetch Mars rover photos from Curiosity and Perseverance by photo ID, Earth date, or Martian sol",
        "homepage": "https://rovers.nebulum.one/",
        "docs_url": "https://rovers.nebulum.one/",
        "license_short": "Free for developers; photo data originates from NASA missions",
        "license_md": "- Free to use for developers, no authentication required\n- Underlying imagery originates from NASA's Mars rover missions and is generally public-domain\n- No explicit licence terms are published by Nebulum; check NASA media usage guidelines when redistributing images\n- CORS is disabled, so browser-based access may require a proxy",
        "about_md": "The [Nebulum Mars Rovers API](https://rovers.nebulum.one/) is a free, no-auth service operated by Nebulum that surfaces photographs taken by NASA's Mars rovers Curiosity (landed August 2012) and Perseverance (landed February 2021). Data is sourced from NASA's own rover photo feeds.\n\nWhat you get from the API:\n\n- Lookup a single photo by its numeric ID: `GET /photos/{id}`\n- List Curiosity photos by Earth date: `GET /rovers/curiosity/photos?earth_date=YYYY-MM-DD`\n- List Curiosity photos by Martian sol: `GET /rovers/curiosity/photos?sol={sol}`\n- List Perseverance photos by Earth date: `GET /rovers/perseverance/photos?earth_date=YYYY-MM-DD`\n- List Perseverance photos by Martian sol: `GET /rovers/perseverance/photos?sol={sol}`\n\nOperational notes: no API key is required, CORS is disabled, and the community catalogue page reports an average response time near 632ms with high recent reliability. Rate limits are not publicly documented.",
        "entity_desc": {
          "photo": "A single rover image record, addressable by numeric ID via `GET /photos/{id}` or listed per rover and date/sol via `GET /rovers/curiosity/photos` and `GET /rovers/perseverance/photos`."
        },
        "auth": false
      },
      "config": {
        "auth": {
          "prefix": "Bearer"
        },
        "headers": {
          "content-type": "application/json"
        },
        "docs_order": [
          "ts",
          "py",
          "php",
          "go",
          "rb",
          "lua"
        ]
      },
      "entity": {
        "photo": {
          "alias": {
            "field": {}
          },
          "fields": [
            {
              "name": "camera",
              "req": false,
              "type": "`$OBJECT`",
              "active": true
            },
            {
              "name": "earth_date",
              "req": false,
              "type": "`$STRING`",
              "active": true
            },
            {
              "name": "id",
              "req": false,
              "type": "`$INTEGER`",
              "active": true
            },
            {
              "name": "img_src",
              "req": false,
              "type": "`$STRING`",
              "active": true
            },
            {
              "name": "rover",
              "req": false,
              "type": "`$OBJECT`",
              "active": true
            },
            {
              "name": "sol",
              "req": false,
              "type": "`$INTEGER`",
              "active": true
            }
          ],
          "id": {
            "field": "id",
            "name": "id"
          },
          "name": "photo",
          "op": {
            "list": {
              "name": "list",
              "points": [
                {
                  "args": {
                    "query": [
                      {
                        "example": "2015-06-03",
                        "kind": "query",
                        "name": "earth_date",
                        "orig": "earth_date",
                        "reqd": false,
                        "type": "`$STRING`",
                        "active": true
                      },
                      {
                        "example": 3718,
                        "kind": "query",
                        "name": "sol",
                        "orig": "sol",
                        "reqd": false,
                        "type": "`$INTEGER`",
                        "active": true
                      }
                    ]
                  },
                  "method": "GET",
                  "orig": "/rovers/curiosity/photos",
                  "parts": [
                    "rovers",
                    "curiosity",
                    "photos"
                  ],
                  "select": {
                    "exist": [
                      "earth_date",
                      "sol"
                    ]
                  },
                  "transform": {
                    "req": "`reqdata`",
                    "res": "`body`"
                  },
                  "active": true
                },
                {
                  "args": {
                    "query": [
                      {
                        "example": "2025-11-06",
                        "kind": "query",
                        "name": "earth_date",
                        "orig": "earth_date",
                        "reqd": false,
                        "type": "`$STRING`",
                        "active": true
                      },
                      {
                        "example": 1676,
                        "kind": "query",
                        "name": "sol",
                        "orig": "sol",
                        "reqd": false,
                        "type": "`$INTEGER`",
                        "active": true
                      }
                    ]
                  },
                  "method": "GET",
                  "orig": "/rovers/perseverance/photos",
                  "parts": [
                    "rovers",
                    "perseverance",
                    "photos"
                  ],
                  "select": {
                    "exist": [
                      "earth_date",
                      "sol"
                    ]
                  },
                  "transform": {
                    "req": "`reqdata`",
                    "res": "`body`"
                  },
                  "active": true
                }
              ],
              "input": "data"
            },
            "load": {
              "name": "load",
              "points": [
                {
                  "args": {
                    "params": [
                      {
                        "example": 878,
                        "kind": "param",
                        "name": "id",
                        "orig": "id",
                        "reqd": true,
                        "type": "`$INTEGER`",
                        "active": true
                      }
                    ]
                  },
                  "method": "GET",
                  "orig": "/photos/{id}",
                  "parts": [
                    "photos",
                    "{id}"
                  ],
                  "select": {
                    "exist": [
                      "id"
                    ]
                  },
                  "transform": {
                    "req": "`reqdata`",
                    "res": "`body`"
                  },
                  "active": true
                }
              ],
              "input": "data"
            }
          },
          "active": true,
          "relations": {
            "ancestors": []
          }
        }
      },
      "feature": {
        "test": {
          "name": "test",
          "title": "In-memory mock transport for testing without a live server",
          "version": "0.0.1",
          "active": true,
          "config": {
            "options": {
              "active": false
            }
          },
          "hook": {
            "PostConstruct": {
              "active": true,
              "await": false
            },
            "PostConstructEntity": {
              "active": true,
              "await": false
            },
            "SetData": {
              "active": true,
              "await": false
            },
            "GetData": {
              "active": true,
              "await": false
            },
            "SetMatch": {
              "active": true
            },
            "GetMatch": {
              "active": true,
              "await": false
            },
            "PrePoint": {
              "active": true
            },
            "PreSpec": {
              "active": true,
              "await": false
            },
            "PreRequest": {
              "active": true,
              "await": false
            },
            "PreResponse": {
              "active": true,
              "await": false
            },
            "PreResult": {
              "active": true,
              "await": false
            },
            "PreTarget": {
              "active": false,
              "await": false
            },
            "PostOperation": {
              "active": false,
              "await": false
            }
          },
          "target": {
            "ts": {
              "deps": {}
            },
            "go": {
              "deps": {}
            },
            "lua": {
              "deps": {}
            },
            "php": {
              "deps": {}
            },
            "py": {
              "deps": {}
            },
            "rb": {
              "deps": {}
            },
            "go-cli": {
              "deps": {}
            },
            "go-mcp": {
              "deps": {}
            }
          }
        }
      },
      "flow": {
        "BasicPhotoFlow": {
          "entity": "photo",
          "kind": "basic",
          "name": "BasicPhotoFlow",
          "step": [
            {
              "op": "list",
              "valid": [
                {
                  "apply": "ItemExists",
                  "def": {
                    "ref": "photo_ref01"
                  }
                }
              ],
              "active": true,
              "match": {},
              "data": {},
              "input": {},
              "spec": []
            },
            {
              "input": {
                "ref": "photo_ref01",
                "srcdatavar": "photo_ref01_data",
                "suffix": "_dt0"
              },
              "match": {
                "id": "photo01"
              },
              "op": "load",
              "valid": [
                {
                  "apply": "TextFieldMark",
                  "def": {
                    "mark": "Mark01-photo_ref01"
                  }
                }
              ],
              "active": true,
              "data": {},
              "spec": []
            }
          ],
          "key$": "BasicPhotoFlow",
          "active": true,
          "param": {}
        }
      },
      "target": {
        "go-cli": {
          "title": "Go CLI",
          "ext": "go",
          "comment": {
            "line": "//"
          },
          "module": {
            "name": "nebulum-mars-rovers"
          },
          "phase": {
            "entity": {
              "active": false
            },
            "feature": {
              "active": false
            },
            "readme": {
              "active": false
            },
            "test": {
              "active": false
            }
          },
          "deps": {},
          "name": "go-cli",
          "active": true
        },
        "go-mcp": {
          "title": "Go MCP server",
          "ext": "go",
          "comment": {
            "line": "//"
          },
          "module": {
            "name": "nebulum-mars-rovers"
          },
          "phase": {
            "entity": {
              "active": false
            },
            "feature": {
              "active": false
            },
            "readme": {
              "active": false
            },
            "test": {
              "active": false
            }
          },
          "deps": {},
          "name": "go-mcp",
          "active": true
        },
        "ts": {
          "title": "TypeScript",
          "ext": "ts",
          "comment": {
            "line": "//"
          },
          "module": {
            "name": "nebulum-mars-rovers"
          },
          "base": "node_modules/@voxgig/sdkgen/project/.sdk",
          "deps": {
            "dotenv": {
              "active": true,
              "version": "^17.4.2",
              "kind": "dev"
            },
            "typescript": {
              "active": true,
              "version": "^5.9.3",
              "kind": "dev"
            },
            "@types/node": {
              "active": true,
              "version": "^25.6.0",
              "kind": "dev"
            }
          },
          "name": "ts",
          "active": true
        },
        "go": {
          "title": "Golang",
          "ext": "go",
          "comment": {
            "line": "//"
          },
          "module": {
            "name": "nebulum-mars-rovers"
          },
          "srcfeature": false,
          "deps": {},
          "name": "go",
          "active": true
        },
        "lua": {
          "title": "Lua",
          "ext": "lua",
          "comment": {
            "line": "--"
          },
          "module": {
            "name": "nebulum-mars-rovers"
          },
          "srcfeature": false,
          "deps": {
            "dkjson": {
              "active": true,
              "version": "2.5",
              "kind": "prod"
            }
          },
          "name": "lua",
          "active": true
        },
        "php": {
          "title": "PHP",
          "ext": "php",
          "comment": {
            "line": "//"
          },
          "module": {
            "name": "nebulum-mars-rovers"
          },
          "srcfeature": false,
          "deps": {},
          "name": "php",
          "active": true
        },
        "py": {
          "title": "Python",
          "ext": "py",
          "comment": {
            "line": "#"
          },
          "module": {
            "name": "nebulum-mars-rovers"
          },
          "srcfeature": false,
          "deps": {
            "requests": {
              "active": true,
              "version": "2.33",
              "kind": "prod"
            }
          },
          "name": "py",
          "active": true
        },
        "rb": {
          "title": "Ruby",
          "ext": "rb",
          "comment": {
            "line": "#"
          },
          "module": {
            "name": "nebulum-mars-rovers"
          },
          "srcfeature": false,
          "deps": {
            "voxgig-struct": {
              "active": true,
              "version": "0.0.10",
              "kind": "prod"
            },
            "json": {
              "active": true,
              "version": "0",
              "kind": "prod"
            }
          },
          "name": "rb",
          "active": true
        }
      },
      "option": {}
    },
    "def": {
      "desc": ""
    }
  }
}